Workbook

Sheet 📋 INSTRUÇÕES
B1: K Controllers | Relatório de Volumetria e Produtividade
A2: Controladoria Jurídica na prática.
B5: COMO USAR ESTE MODELO
B7: ① ABA ➜ BASE DE DADOS
B8: Cole aqui os dados exportados do seu sistema de gestão.
B9: Cada linha = 1 processo ou 1 prazo.
B10: Não altere os cabeçalhos - as fórmulas dependem deles.
B12: ② ABA ➜ VOLUMETRIA DE PROCESSOS
B13: Atualiza automaticamente a partir da BASE DE DADOS.
B14: Mostra: total por área, por fase, por advogado e curva de ajuizamento.
B16: ③ ABA ➜ PRODUTIVIDADE E PRAZOS
B17: Atualiza automaticamente. Não edite as células com fórmulas.
B18: Mostra: prazos por tipo, taxa de cumprimento, performance por advogado.
B20: DICAS IMPORTANTES
... B34: kcontrollers.com.br | Uso exclusivo K Controllers

Sheet BASE DE DADOS
A1: SEÇÃO 1 — PROCESSOS | I1: SEÇÃO 2 — PRAZOS
A2: Preencha uma linha por processo ativo. Não deixe linhas em branco no meio. | I2: Preencha um prazo por linha. Status: Cumprido | Pendente | Não cumprido
A3: Nº Processo | B3: Área / Matéria | C3: Fase Processual | D3: Responsável (Advogado) | E3: Data Ajuizamento | F3: Vara / Tribunal | G3: Observação | I3: Nº Processo | J3: Tipo de Prazo | K3: Data Limite | L3: Responsável (Advogado) | M3: Status do Prazo | N3: Data Cumprimento | O3: Observação
A4: 5005212-03.2026.8.24.0020 | B4: Outras | D4: Renata Francisco Becker | E4: 46002 | I4: 01560009520055120033 | J4: Tarefa | K4: 46027 | L4: Pedro Victor | M4: Cumprido | N4: 46027 | O4: Pedido de redução de desconto
A5: 5008937-34.2025.8.24.0020 | B5: Outras | D5: Renata Francisco Becker | E5: 45769 | F5: 2° vara cível | J5: Tarefa | K5: 46027 | L5: Julia | M5: Cumprido | N5: 46027 | O5: Registro de Marca Reficel e Valen
B6: Outras | D6: Marelize Controladoria | E6: 46073 | J6: Evento | K6: 46027 | L6: Marelize Controladoria | M6: Cumprido | N6: 46027 | O6: Reunião controladoria (Nathalia)
A7: 5001371-18.2024.8.24.0166 | B7: Outras | D7: Renata Francisco Becker | E7: 45448 | J7: Tarefa | K7: 46028 | L7: Marelize Controladoria | M7: Cumprido | N7: 46028 | O7: Lize, consegue aplicar o cronograma do Lucas, na agenda dele, conforme conversamos. Se conseguir fazer antes do retorno dele, agradeço,
A8: 0301909-52.2015.8.24.0028 | B8: Outras | D8: Marelize Controladoria | E8: 46105 | F8: Juízo da 1ª Vara Cível da Comarca de Içara | I8: 40013348420268260100 | J8: Tarefa | K8: 46029 | L8: Renata Francisco Becker | M8: Cumprido | N8: 46029 | O8: CONFERÊNCIA IMPORTANTE MI - Cobrança Monto - MMC
A9: 5000212-03.2018.8.24.0020 | B9: Outras | D9: Renata Francisco Becker | E9: 44761 | F9: Juízo da 2ª Vara Cível da Comarca de Criciúma | J9: Tarefa | K9: 46029 | L9: Marelize Controladoria | M9: Cumprido | N9: 46029 | O9: Por favor, consegue verificar como funciona essa questão no Astrea de atividades pré definidas. Para podermos implementar… Segundo o Astrea, ótima o tempo da distribuição das publicacoes
B10: Outras | D10: Marelize Controladoria | E10: 46100 | J10: Tarefa | K10: 46029 | L10: Marelize Controladoria | M10: Cumprido | N10: 46029 | O10: DISTRIBUIR TAREFAS (Pedro grupo controladoria)
A11: 5133128-39.2026.8.09.0084 | B11: Outras | D11: Marelize Controladoria | E11: 46071 | I11: 5020941-06.2025.8.24.0020 | J11: Tarefa | K11: 46029 | L11: Marelize Controladoria | M11: Cumprido | N11: 46029 | O11: Redesignado audiencia, avisar cliente, anotar nas agendas
A12: 50055518420238240078 | B12: Outras | D12: Renata Francisco Becker | E12: 45338 | J12: Evento | K12: 46029 | L12: Renata Francisco Becker | M12: Cumprido | N12: 46029 | O12: Reunião Nika - pavilhao
B13: Outras | D13: Pedro Victor | E13: 46059 | J13: Evento | K13: 46029 | L13: Renata Francisco Becker | M13: Cumprido | N13: 46029 | O13: Atendimento Renata
A14: 0028206-72.2010.8.24.0020 | B14: Outras | D14: Renata Francisco Becker | E14: 45685 | F14: Vara da Família | J14: Prazo | K14: 46030 | L14: Alexia | M14: Cumprido | N14: 46030 | O14: Prazo 19.12-defesa-prorrogação
B15: Outras | D15: Marelize Controladoria | E15: 46080 | J15: Tarefa | K15: 46030 | L15: Julia | M15: Cumprido | N15: 46030 | O15: FAZER AÇÃO RECISÓRIA CONTRATUAL
A16: 0001022-55.2025.5.12.0003 | B16: Outras | D16: Renata Francisco Becker | E16: 45890 | F16: Vara do Trabalho | J16: Tarefa | K16: 46030 | L16: Marelize Controladoria | M16: Cumprido | N16: 46030 | O16: Verificar demanda Perdoná
A17: 5012554-02.2025.8.24.0020 | B17: Outras | D17: Renata Francisco Becker | E17: 45813 | J17: Tarefa | K17: 46030 | L17: Jessica | M17: Cumprido | N17: 46030 | O17: PLANEJAMENTO TRIBUTÁRIO DA PAPA JOHN
B18: Outras | D18: Marelize Controladoria | E18: 46072 | J18: Tarefa | K18: 46030 | L18: Julia | M18: Cumprido | N18: 46030 | O18: Análise de Contratos Adicionais Ação: Analisar e revisar dois modelos de contrato de grande porte utilizados pela Granda Engenharia.
A19: 5000200-62.2025.8.24.0175 | B19: Outras | D19: Renata Francisco Becker | E19: 45786 | F19: Vara Única | I19: 50000591320248240940 | J19: Tarefa | K19: 46030 | L19: Jessica | M19: Cumprido | N19: 46030 | O19: Conferir CDA juntada no PAF com a do processo para ver se é exatamente a mesma
A20: 5003424-51.2026.8.24.0020 | B20: Outras | D20: Marelize Controladoria | E20: 46099 | F20: Juízo da 4ª Vara Cível da Comarca de Criciúma | J20: Tarefa | K20: 46030 | L20: Lucas | M20: Cumprido | N20: 46030 | O20: Fazer regimento interno.
A21: 0000459-98.2025.5.12.0023 | B21: Outras | D21: Luci | E21: 45779 | J21: Tarefa | K21: 46030 | L21: Julia | M21: Cumprido | N21: 46030 | O21: Joel pediu para analisar a declaração de ciencia e autorização para protocolo e ver o que posso aprimorar - pediu para Julia na reuniao do dia 17/12/2025
A22: 0028824-87.2025.8.19.0001 | B22: Outras | D22: Renata Francisco Becker | E22: 45727 | F22: 2° Vara Especializada | J22: Evento | K22: 46030 | L22: Marelize Controladoria | M22: Cumprido | N22: 46030 | O22: Reunião inicial com a Karia - IMPLEMENTAÇÃO
A23: 1025830-78.2026.8.26.0053 | B23: Outras | D23: Marelize Controladoria | E23: 46087 | F23: 7ª Vara de Fazenda Pública | J23: Evento | K23: 46030 | L23: Renata Francisco Becker | M23: Cumprido | N23: 46030 | O23: Atendimento inventario Jessica
A24: 5024640-10.2022.8.24.0020 | B24: Outras | D24: Renata Francisco Becker | E24: 44858 | J24: Prazo | K24: 46031 | L24: Julia | M24: Cumprido | N24: 46031 | O24: Atualizar contrato de tercerização
A25: 0005476-39.2025.8.26.0100 | B25: Outras | D25: Marelize Controladoria | E25: 46059 | F25: 1ª Vara de Falências e Recuperações Judiciais | J25: Prazo | K25: 46031 | L25: Lucas | M25: Cumprido | N25: 46031 | O25: Demanda Expresso Veneza (Lucas)
A26: 5005551-84.2023.8.24.0078 | B26: Outras | D26: Pedro Victor | E26: 45337 | F26: Vara Cível | J26: Prazo | K26: 46031 | L26: Lucas | M26: Cumprido | N26: 46031 | O26: Demanda Vonscher (DET)
A27: 5011984-50.2024.8.24.0020 | B27: Outras | D27: Renata Francisco Becker | E27: 45426 | F27: Vara Cível | I27: 09.2022.00002328-6 | J27: Prazo | K27: 46031 | L27: Lucas | M27: Cumprido | N27: 46031 | O27: Prazo
A28: 0001682-49.2025.5.12.0003 | B28: Outras | D28: Marelize Controladoria | E28: 46035 | F28: 1ª VARA DO TRABALHO DE CRICIÚMA | I28: 5006390-88.2025.8.24.0030 | J28: Prazo | K28: 46031 | L28: Renata Francisco Becker | M28: Cumprido | N28: 46031 | O28: Prazo Crime
A29: 5004196-94.2020.4.04.7204 | B29: Outras | D29: Renata Francisco Becker | E29: 44789 | F29: Juízo Federal da 4ª VF de Criciúma | J29: Prazo | K29: 46031 | L29: Jessica | M29: Cumprido | N29: 46031 | O29: prazo pedido caducidade
A30: 5012167-67.2019.4.04.7204 | B30: Outras | D30: Renata Francisco Becker | E30: 44725 | F30: Juízo Substituto da 4ª VF de Criciúma | I30: 5005478-34.2024.8.24.0028 | J30: Prazo | K30: 46031 | L30: Renata Francisco Becker | M30: Cumprido | N30: 46031 | O30: RENUNCIA RECAPADORA
A31: 5000429-88.2021.8.24.0166 | B31: Outras | D31: Renata Francisco Becker | E31: 44701 | F31: Juizo Da Vara Unica Da Comarca De Forquilhinha | J31: Tarefa | K31: 46031 | L31: Lucas | M31: Cumprido | N31: 46031 | O31: 09/01/2026 - CONFERIR ATIVIDADES MONITORADAS
A32: 5004194-27.2020.4.04.7204 | B32: Outras | D32: Renata Francisco Becker | E32: 44798 | F32: 4 | J32: Tarefa | K32: 46031 | L32: Renata Francisco Becker | M32: Cumprido | N32: 46031 | O32: Elaboração
A33: 5012238-69.2019.4.04.7204 | B33: Outras | D33: Renata Francisco Becker | E33: 44719 | F33: Juízo Federal da 4ª VF de Criciúma | I33: 09.2022.00002328-6 | J33: Tarefa | K33: 46031 | L33: Lucas | M33: Cumprido | N33: 46031 | O33: Elaboração
A34: 5020732-76.2021.8.24.0020 | B34: Outras | D34: Renata Francisco Becker | E34: 44781 | F34: Juízo da Vara da Infância e Juventude e Anexos da Comarca de Criciúma | J34: Tarefa | K34: 46031 | L34: Julia | M34: Cumprido | N34: 46031 | O34: Elaboração
A35: 1000101-23.2021.8.26.0539 | B35: Outras | D35: Renata Francisco Becker | E35: 45764 | F35: 3ª Vara Cível | J35: Tarefa | K35: 46031 | L35: Renata Francisco Becker | M35: Cumprido | N35: 46031 | O35: Finalizar agenda Lucas (jud e adm)
A36: 5032306-91.2024.8.24.0020 | B36: Outras | D36: Pedro Victor | E36: 45593 | I36: 09.2022.00002328-6 | J36: Tarefa | K36: 46031 | L36: Lucas | M36: Cumprido | N36: 46031 | O36: Protocolo
A37: 5017084-75.2026.8.24.0000 | B37: Outras | D37: Pedro Victor | E37: 46084 | J37: Tarefa | K37: 46031 | L37: Julia | M37: Cumprido | N37: 46031 | O37: REVISAR URGENTE - Notificação de devolução de valores - Mega Máquinas
B38: Outras | D38: Marelize Controladoria | E38: 46052 | I38: 09.2022.00002328-6 | J38: Tarefa | K38: 46031 | L38: Renata Francisco Becker | M38: Cumprido | N38: 46031 | O38: Revisão
A39: 03063527020158240020 | B39: Outras | D39: Pedro Victor | E39: 45877 | F39: Juízo da 1ª Vara da Fazenda Pública da Comarca de Criciúma | I39: 09.2022.00002328-6 | J39: Tarefa | K39: 46031 | L39: Lucas | M39: Cumprido | N39: 46031 | O39: Revisão
B40: Outras | D40: Marelize Controladoria | E40: 46083 | J40: Tarefa | K40: 46031 | L40: Julia | M40: Cumprido | N40: 46031 | O40: Revisão
A41: 50061056220248240020 | B41: Outras | D41: Renata Francisco Becker | E41: 45370 | J41: Tarefa | K41: 46031 | L41: Marelize Controladoria | M41: Cumprido | N41: 46031 | O41: VERIFICAR PINK - LU/JESS/ALE/JU
B42: Outras | D42: Renata Francisco Becker | E42: 45541 | I42: 0000500-51.2025.5.12.0060 | J42: Tarefa | K42: 46031 | L42: Lucas | M42: Cumprido | N42: 46031 | O42: 14/01/2026 - Cobrar Paulo do pagamenrto da parcela. Wnviar o pix para pagamento hasckelr@hotmail.com PArcela de R$1.000,00
A43: 0001360-54.2025.5.12.0027 | B43: Outras | D43: Renata Francisco Becker | E43: 45926 | F43: Vara do Trabalho | I43: 0000500-51.2025.5.12.0060 | J43: Tarefa | K43: 46031 | L43: Lucas | M43: Cumprido | N43: 46031 | O43: 14/12/2025 - Cobrar Paulo do pagamenrto da parcela. Wnviar o pix para pagamento hasckelr@hotmail.com PArcela de R$1.000,00
A44: 0000579-26.2017.5.12.0055 | B44: Outras | D44: Renata Francisco Becker | E44: 44844 | J44: Tarefa | K44: 46031 | L44: Marelize Controladoria | M44: Cumprido | N44: 46031 | O44: AGENDAR - @Marelize agenda pra mim uma reunião de apresentação de assessoria para o Ramon Demarch na semana que vem.
A45: 5012243-91.2019.4.04.7204 | B45: Outras | D45: Renata Francisco Becker | E45: 44706 | F45: Juízo Federal da 1ª VF de Tubarão | J45: Tarefa | K45: 46031 | L45: Alexia | M45: Cumprido | N45: 46031 | O45: Ação Pedagio
A46: 5000981-30.2026.8.24.0020 | B46: Outras | D46: Marelize Controladoria | E46: 46045 | F46: Juízo do Juizado Especial Cível da Comarca de Criciúma | J46: Tarefa | K46: 46031 | L46: Jessica | M46: Cumprido | N46: 46031 | O46: conferir contratos sociais feitos pelo Edivanio -
A47: 0000254-62.2026.5.12.0014 | B47: Outras | D47: Marelize Controladoria | E47: 46077 | J47: Tarefa | K47: 46031 | L47: Lucas | M47: Cumprido | N47: 46031 | O47: Criar e implementar o regimento interno
A48: 5030127-53.2025.8.24.0020 | B48: Outras | D48: Marelize Controladoria | E48: 46090 | F48: Juízo da 4ª Vara Cível da Comarca de Criciúma | J48: Tarefa | K48: 46031 | L48: Julia | M48: Cumprido | N48: 46031 | O48: Elaboração
A49: 5065946-13.2023.8.24.0023 | B49: Outras | D49: Renata Francisco Becker | E49: 45412 | J49: Tarefa | K49: 46031 | L49: Julia | M49: Cumprido | N49: 46031 | O49: Fazer cobrança adm, olha no histórico do caso. Não temos a nota fiscal, vamos entrar em contato (48-8808-1759) para ver se conseguimos um acordo na esfera adm.
B50: Outras | D50: Marelize Controladoria | E50: 46056 | J50: Tarefa | K50: 46031 | L50: Lucas | M50: Cumprido | N50: 46031 | O50: Fazer um checkout de todas as empresas. verificar se todas as assessorias estão cadastradas no astrea. as que não estiverem, cadastrar. as que estiverem verificar se estão alimentadas com o máximo de informações importantes. se não, alimentar.
A51: 5000678-95.2026.8.24.0026 | B51: Outras | D51: Marelize Controladoria | E51: 46059 | F51: Juízo da 2ª Vara Cível da Comarca de Guaramirim | I51: 5004339-47.2024.8.24.0028 | J51: Tarefa | K51: 46031 | L51: Julia | M51: Cumprido | N51: 46031 | O51: Julia acompanhar, se cartório expedio oficio para tabelionato para averbar o divórcio.
A52: 0310761-21.2017.8.24.0020 | B52: Outras | D52: Renata Francisco Becker | E52: 44705 | F52: Juízo da 2ª Vara Cível da Comarca de Criciúma | J52: Tarefa | K52: 46031 | L52: Lucas | M52: Cumprido | N52: 46031 | O52: Melhorar documentos únicos das empresas - Acrescentar termo de compromisso Regimento
A53: 4000166-33.2026.8.26.0428 | B53: Outras | D53: Marelize Controladoria | E53: 46100 | F53: Juízo Titular I - Vara do Juizado Especial Cível e Criminal da Comarca de Paulínia | J53: Tarefa | K53: 46031 | L53: Jessica | M53: Cumprido | N53: 46031 | O53: peticionar no processo MMC pedindo a extinção do crédito tributário pelo pagamento
A54: 0000168-46.2018.5.12.0055 | B54: Outras | D54: Renata Francisco Becker | E54: 44754 | F54: 4ª VARA DO TRABALHO DE CRICIÚMA | J54: Tarefa | K54: 46031 | L54: Renata Francisco Becker | M54: Cumprido | N54: 46031 | O54: RESTITUIÇÃO DE VALORES TLZ
A55: 5005921-60.2026.8.24.0045 | B55: Outras | D55: Renata Francisco Becker | E55: 46073 | F55: Juízo do Juizado Especial Cível da Comarca de Palhoça | J55: Tarefa | K55: 46031 | L55: Renata Francisco Becker | M55: Cumprido | N55: 46031 | O55: Revisão
B56: Outras | D56: Marelize Controladoria | E56: 46097 | J56: Tarefa | K56: 46031 | L56: Jessica | M56: Cumprido | N56: 46031 | O56: revisão contrato social escritorio
A57: 5033611-13.2024.8.24.0020 | B57: Outras | D57: Renata Francisco Becker | E57: 45706 | J57: Tarefa | K57: 46031 | L57: Jessica | M57: Cumprido | N57: 46031 | O57: Solicitação de documentação
A58: 0000994-78.2025.5.12.0006 | B58: Outras | D58: Renata Francisco Becker | E58: 45925 | F58: Vara do Trabalho | J58: Evento | K58: 46031 | L58: Marelize Controladoria | M58: Cumprido | N58: 46031 | O58: Reunião (Empresa TLZ)
A59: 5002681-95.2025.8.24.0078 | B59: Outras | D59: Renata Francisco Becker | E59: 45849 | F59: Vara | J59: Evento | K59: 46031 | L59: Marelize Controladoria | M59: Cumprido | N59: 46031 | O59: Entrevista com Nathalia - Jessica
A60: 5100017-65.2025.8.24.0930 | B60: Outras | D60: Renata Francisco Becker | E60: 45905 | F60: Vara Estadual | J60: Evento | K60: 46031 | L60: Marelize Controladoria | M60: Cumprido | N60: 46031 | O60: Entrevista com Nathalia - Julia
A61: 0000958-45.2025.512.0003 | B61: Outras | D61: Lucas | E61: 45953 | F61: Vara do Trabalho | J61: Evento | K61: 46031 | L61: Marelize Controladoria | M61: Cumprido | N61: 46031 | O61: Consulta/Atendimento (Dhido)
A62: 5012877-07.2025.8.24.0020 | B62: Outras | D62: Pedro Victor | E62: 45862 | F62: Juízo do Juizado Especial Cível da Comarca de Criciúma | I62: 5030853-27.2025.8.24.0020 | J62: Prazo | K62: 46034 | L62: Jessica | M62: Cumprido | N62: 46034 | O62: Agravo de Instrumento
A63: 00970636220251000000 | B63: Outras | D63: Pedro Victor | E63: 45723 | J63: Prazo | K63: 46034 | L63: Julia | M63: Cumprido | N63: 46034 | O63: Analise de contrato
A64: 50035098120248240028 | B64: Outras | D64: Renata Francisco Becker | E64: 45464 | I64: 5000966-52.2024.8.24.0078 | J64: Prazo | K64: 46034 | L64: Alexia | M64: Cumprido | N64: 46034 | O64: Apelação - Improcende irmãos
A65: 5025747-21.2024.8.24.0020 | B65: Outras | D65: Renata Francisco Becker | E65: 45709 | F65: Vara Cível | J65: Prazo | K65: 46034 | L65: Lucas | M65: Cumprido | N65: 46034 | O65: Auditoria Trabalhista Expresso Tubarão
A66: 5033971-45.2024.8.24.0020 | B66: Outras | D66: Renata Francisco Becker | E66: 45554 | F66: Vara Cível | J66: Prazo | K66: 46034 | L66: Lucas | M66: Cumprido | N66: 46034 | O66: Auditoria Trabalhista Expresso Veneza
A67: 0301827-94.2017.8.24.0175 | B67: Outras | D67: Renata Francisco Becker | E67: 44701 | F67: 5º Juizo Da Unidade Estadual De Direito Bancario | J67: Prazo | K67: 46034 | L67: Lucas | M67: Cumprido | N67: 46034 | O67: Confecção de carta trabalhista
A68: 5035736-77.2025.8.24.0000 | B68: Outras | D68: Renata Francisco Becker | E68: 45790 | F68: 8ª Câmara de Direito Civil | J68: Prazo | K68: 46034 | L68: Julia | M68: Cumprido | N68: 46034 | O68: Contranotificação
A69: 5002233-41.2026.4.04.7204 | B69: Outras | D69: Marelize Controladoria | E69: 46086 | F69: Juízo Substituto da 9ª VF de Florianópolis | I69: 50142582320254047204 | J69: Prazo | K69: 46034 | L69: Jessica | M69: Cumprido | N69: 46034 | O69: Emendar a inicial MS
A70: 50022017320258240028 | B70: Outras | D70: Pedro Victor | E70: 45782 | F70: Juízo da Vara Criminal da Comarca de Içara | I70: 0003005-61.2025.8.16.0154 | J70: Prazo | K70: 46034 | L70: Renata Francisco Becker | M70: Cumprido | N70: 46034 | O70: Prazo
A71: 1192002-34.2024.8.26.0100 | B71: Outras | D71: Pedro Victor | E71: 45839 | F71: Falências | I71: 5004094-23.2023.8.24.0076 | J71: Prazo | K71: 46034 | L71: Renata Francisco Becker | M71: Cumprido | N71: 46034 | O71: prazo
A72: 5004199-49.2020.4.04.7204 | B72: Outras | D72: Renata Francisco Becker | E72: 44805 | F72: Juízo Federal da 4ª VF de Criciúma | I72: 5000123-81.2025.8.24.0004 | J72: Prazo | K72: 46034 | L72: Renata Francisco Becker | M72: Cumprido | N72: 46034 | O72: Prazo (PF - 05.02)
A73: 5069978-85.2025.8.24.0930 | B73: Outras | D73: Renata Francisco Becker | E73: 45938 | F73: Vara Estadual de Direito Bancário | I73: 5006390-88.2025.8.24.0030 | J73: Prazo | K73: 46034 | L73: Renata Francisco Becker | M73: Cumprido | N73: 46034 | O73: Prazo 26/01 (audiência)
A74: 5007675-95.2020.4.04.7204 | B74: Outras | D74: Renata Francisco Becker | E74: 44840 | I74: 5011984-50.2024.8.24.0020 | J74: Prazo | K74: 46034 | L74: Renata Francisco Becker | M74: Cumprido | N74: 46034 | O74: Prazo Rodrigo pizza
A75: 50235352720248240020 | B75: Outras | D75: Renata Francisco Becker | E75: 45588 | I75: 5000966-52.2024.8.24.0078 | J75: Tarefa | K75: 46034 | L75: Alexia | M75: Cumprido | N75: 46034 | O75: Elaboração
A76: 5001271-45.2026.8.24.0020 | B76: Outras | D76: Marelize Controladoria | E76: 46048 | F76: Juízo do Juizado Especial Cível da Comarca de Criciúma | I76: 5030853-27.2025.8.24.0020 | J76: Tarefa | K76: 46034 | L76: Jessica | M76: Cumprido | N76: 46034 | O76: Elaboração
A77: 50041917220204047204 | B77: Outras | D77: Renata Francisco Becker | E77: 44812 | J77: Tarefa | K77: 46034 | L77: Julia | M77: Cumprido | N77: 46034 | O77: Elaboração
A78: 5000537-54.2020.8.24.0166 | B78: Outras | D78: Renata Francisco Becker | E78: 44720 | F78: Juízo da Vara Única da Comarca de Forquilhinha | I78: 5011984-50.2024.8.24.0020 | J78: Tarefa | K78: 46034 | L78: Renata Francisco Becker | M78: Cumprido | N78: 46034 | O78: Elaboração
A79: 5008261-61.2019.8.24.0064 | B79: Outras | D79: Renata Francisco Becker | E79: 45155 | F79: Juízo da 3ª Vara Cível da Comarca de São José | I79: 0003005-61.2025.8.16.0154 | J79: Tarefa | K79: 46034 | L79: Renata Francisco Becker | M79: Cumprido | N79: 46034 | O79: Elaboração
A80: 5028872-60.2025.8.24.0020 | B80: Outras | D80: Renata Francisco Becker | E80: 46007 | J80: Tarefa | K80: 46034 | L80: Lucas | M80: Cumprido | N80: 46034 | O80: Elaboração (Confecção de documetos)
B81: Outras | D81: Marelize Controladoria | E81: 46100 | J81: Tarefa | K81: 46034 | L81: Lucas | M81: Cumprido | N81: 46034 | O81: Elaboração (Confecção de documetos)
A82: 0117600-68.2006.5.12.0003 | B82: Outras | D82: Renata Francisco Becker | E82: 45986 | F82: Vara do Trabalho | J82: Tarefa | K82: 46034 | L82: Renata Francisco Becker | M82: Cumprido | N82: 46034 | O82: Revisão
A83: 50313185620248240930 | B83: Outras | D83: Renata Francisco Becker | E83: 45455 | J83: Tarefa | K83: 46034 | L83: Renata Francisco Becker | M83: Cumprido | N83: 46034 | O83: Revisão
B84: Outras | D84: Marelize Controladoria | E84: 46100 | J84: Tarefa | K84: 46034 | L84: Renata Francisco Becker | M84: Cumprido | N84: 46034 | O84: Revisão
A85: 0000148-36.2026.5.12.0003 | B85: Outras | D85: Luci | E85: 45742 | J85: Tarefa | K85: 46034 | L85: Jessica | M85: Cumprido | N85: 46034 | O85: 24/11/2025 - EMITIR GUIAS TRANSAÇÃO SIDNEI - portal Regularize - enviar até dia 27 de cada mês
A86: 5023389-83.2024.8.24.0020 | B86: Outras | D86: Pedro Victor | E86: 46100 | F86: Juízo da Vara Regional de Garantias da Comarca de Criciúma | J86: Tarefa | K86: 46034 | L86: Pedro Victor | M86: Cumprido | N86: 46034 | O86: Analisar a ação de demarcação de terra, com pedido de tutela para nao haver dano à obra do imóvel
A87: 0323800-69.2005.5.12.0027 | B87: Outras | D87: Renata Francisco Becker | E87: 45930 | I87: 5005212-03.2026.8.24.0020 | J87: Tarefa | K87: 46034 | L87: Julia | M87: Cumprido | N87: 46034 | O87: Cobrança - Julia, seguir nosso pop de cobrança
A88: 5031729-60.2025.4.03.0000 | B88: Outras | D88: Jessica | E88: 45987 | J88: Tarefa | K88: 46034 | L88: Renata Francisco Becker | M88: Cumprido | N88: 46034 | O88: Contrato aluguel lahoa
A89: 50116018620258240004 | B89: Outras | D89: Renata Francisco Becker | E89: 45883 | F89: 3° Vara Civel | I89: 5003445-90.2025.8.24.0075 | J89: Tarefa | K89: 46034 | L89: Marelize Controladoria | M89: Cumprido | N89: 46034 | O89: Controler, cadastrar o processo 5003445-90.2025.8.24.0075 no astrea, fomos nomeados. E, distribuir para apresentaçaõ de contestaçaõ, prazo 28.01. gratidao
A90: 50127492120248240020 | B90: Outras | D90: Renata Francisco Becker | E90: 45433 | J90: Tarefa | K90: 46034 | L90: Jessica | M90: Cumprido | N90: 46034 | O90: Elaboração de clausula tributária
A91: 5031701-14.2025.8.24.0020 | B91: Outras | D91: Renata Francisco Becker | E91: 45931 | F91: Juízo do Juizado Especial Cível da Comarca de Criciúma | J91: Tarefa | K91: 46034 | L91: Renata Francisco Becker | M91: Cumprido | N91: 46034 | O91: Juntar renuncia recapadora.
A92: 5025749-54.2025.8.24.0020 | B92: Outras | D92: Renata Francisco Becker | E92: 45946 | F92: 1° vara | J92: Tarefa | K92: 46034 | L92: Renata Francisco Becker | M92: Cumprido | N92: 46034 | O92: Revisão
A93: 5000454-41.2025.8.24.0076 | B93: Outras | D93: Renata Francisco Becker | E93: 45716 | F93: Juizo da vara unica | J93: Evento | K93: 46034 | L93: Marelize Controladoria | M93: Cumprido | N93: 46034 | O93: Entrevista com Nathalia - Alexia
A94: 0000198-62.2026.5.12.0003 | B94: Outras | D94: Marelize Controladoria | E94: 46086 | F94: CEJUSC-JT/Criciuma | J94: Evento | K94: 46034 | L94: Marelize Controladoria | M94: Cumprido | N94: 46034 | O94: Entrevista com Nathalia - Lucas
A95: 5038732-76.2025.8.24.0023 | B95: Outras | D95: Pedro Victor | E95: 45772 | F95: Fazenda Publica | J95: Evento | K95: 46034 | L95: Marelize Controladoria | M95: Cumprido | N95: 46034 | O95: Reunião Ex Marília
A96: 0000372-71.2026.5.12.0003 | B96: Outras | D96: Luci | E96: 46084 | F96: 1 | I96: 5002987-34.2025.8.24.0282 | J96: Prazo | K96: 46035 | L96: Renata Francisco Becker | M96: Cumprido | N96: 46035 | O96: 26/01 Prazo Colomboretroterra (crime)
B97: Outras | D97: Pedro Victor | E97: 46048 | J97: Prazo | K97: 46035 | L97: Renata Francisco Becker | M97: Cumprido | N97: 46035 | O97: Analisar contrato Ex. Marília
A98: 5011355-42.2025.8.24.0020 | B98: Outras | D98: Renata Francisco Becker | E98: 45806 | J98: Prazo | K98: 46035 | L98: Renata Francisco Becker | M98: Cumprido | N98: 46035 | O98: Analise de contrato
A99: 5003082-74.2025.8.24.0020 | B99: Outras | D99: Marelize Controladoria | E99: 46057 | F99: Juízo da 2ª Vara da Fazenda Pública da Comarca de Criciúma | I99: 5008146-31.2024.8.24.0075 | J99: Prazo | K99: 46035 | L99: Renata Francisco Becker | M99: Cumprido | N99: 46035 | O99: Apelação nomeação. olhar
A100: 5012267-22.2019.4.04.7204 | B100: Outras | D100: Renata Francisco Becker | E100: 44719 | F100: Juízo Federal da 4ª VF de Criciúma | J100: Prazo | K100: 46035 | L100: Renata Francisco Becker | M100: Cumprido | N100: 46035 | O100: AÇÃO RESCISÓRIA CONTRATUAL
...

Sheet VOLUMETRIA DE PROCESSOS
A1: VOLUMETRIA DE PROCESSOS
A2: Atualização automática a partir da BASE DE DADOS | Não edite esta aba
B4: PROCESSOS POR ÁREA / MATÉRIA | G4: PROCESSOS POR FASE PROCESSUAL
B5: Área / Matéria | C5: Qtd. Processos | D5: % do Total | G5: Fase Processual | H5: Qtd. Processos | I5: % do Total
B6: Cível | C6: =COUNTIF('BASE DE DADOS'!$B$4:$B$3000,B6) | D6: =IF(C6=0,"-",TEXT(C6/C14,"0.0%")) | G6: Conhecimento | H6: =COUNTIF('BASE DE DADOS'!$C$4:$C$3000,G6) | I6: =IF(H6=0,"-",TEXT(H6/H13,"0.0%"))
B7: Trabalhista | C7: =COUNTIF('BASE DE DADOS'!$B$4:$B$3000,B7) | D7: =IF(C7=0,"-",TEXT(C7/C14,"0.0%")) | G7: Recurso | H7: =COUNTIF('BASE DE DADOS'!$C$4:$C$3000,G7) | I7: =IF(H7=0,"-",TEXT(H7/H13,"0.0%"))
B8: Tributário | C8: =COUNTIF('BASE DE DADOS'!$B$4:$B$3000,B8) | D8: =IF(C8=0,"-",TEXT(C8/C14,"0.0%")) | G8: Execução | H8: =COUNTIF('BASE DE DADOS'!$C$4:$C$3000,G8) | I8: =IF(H8=0,"-",TEXT(H8/H13,"0.0%"))
B9: Previdenciário | C9: =COUNTIF('BASE DE DADOS'!$B$4:$B$3000,B9) | D9: =IF(C9=0,"-",TEXT(C9/C14,"0.0%")) | G9: Cumprimento de Sentença | H9: =COUNTIF('BASE DE DADOS'!$C$4:$C$3000,G9) | I9: =IF(H9=0,"-",TEXT(H9/H13,"0.0%"))
B10: Criminal | C10: =COUNTIF('BASE DE DADOS'!$B$4:$B$3000,B10) | D10: =IF(C10=0,"-",TEXT(C10/C14,"0.0%")) | G10: Transitado em Julgado | H10: =COUNTIF('BASE DE DADOS'!$C$4:$C$3000,G10) | I10: =IF(H10=0,"-",TEXT(H10/H13,"0.0%"))
B11: Família | C11: =COUNTIF('BASE DE DADOS'!$B$4:$B$3000,B11) | D11: =IF(C11=0,"-",TEXT(C11/C14,"0.0%")) | G11: Suspenso | H11: =COUNTIF('BASE DE DADOS'!$C$4:$C$3000,G11) | I11: =IF(H11=0,"-",TEXT(H11/H13,"0.0%"))
B12: Empresarial | C12: =COUNTIF('BASE DE DADOS'!$B$4:$B$3000,B12) | D12: =IF(C12=0,"-",TEXT(C12/C14,"0.0%")) | G12: Arquivado | H12: =COUNTIF('BASE DE DADOS'!$C$4:$C$3000,G12) | I12: =IF(H12=0,"-",TEXT(H12/H13,"0.0%"))
B13: Outras | C13: =COUNTIF('BASE DE DADOS'!$B$4:$B$3000,B13) | D13: =IF(C13=0,"-",TEXT(C13/C14,"0.0%")) | G13: TOTAL | H13: =SUM(H6:H12)
B14: TOTAL | C14: =SUM(C6:C13)
B16: PROCESSOS POR RESPONSÁVEL (ADVOGADO)
B17: Responsável | C17: Qtd. Processos | D17: % do Total
B18: Jessica | C18: =IF(B18="","",COUNTIF('BASE DE DADOS'!$D$4:$D$3000,B18)) | D18: =IF(OR(B18="",C18=0),"-",TEXT(C18/C14,"0.0%"))
B19: Julia | C19: =IF(B19="","",COUNTIF('BASE DE DADOS'!$D$4:$D$3000,B19)) | D19: =IF(OR(B19="",C19=0),"-",TEXT(C19/C14,"0.0%"))
B20: Lucas | C20: =IF(B20="","",COUNTIF('BASE DE DADOS'!$D$4:$D$3000,B20)) | D20: =IF(OR(B20="",C20=0),"-",TEXT(C20/C14,"0.0%"))
B21: Luci | C21: =IF(B21="","",COUNTIF('BASE DE DADOS'!$D$4:$D$3000,B21)) | D21: =IF(OR(B21="",C21=0),"-",TEXT(C21/C14,"0.0%"))
B22: Marelize Controladoria | C22: =IF(B22="","",COUNTIF('BASE DE DADOS'!$D$4:$D$3000,B22)) | D22: =IF(OR(B22="",C22=0),"-",TEXT(C22/C14,"0.0%"))
B23: Pedro Victor | C23: =IF(B23="","",COUNTIF('BASE DE DADOS'!$D$4:$D$3000,B23)) | D23: =IF(OR(B23="",C23=0),"-",TEXT(C23/C14,"0.0%"))
B24: Renata Francisco Becker | C24: =IF(B24="","",COUNTIF('BASE DE DADOS'!$D$4:$D$3000,B24)) | D24: =IF(OR(B24="",C24=0),"-",TEXT(C24/C14,"0.0%"))
B27: CURVA DE AJUIZAMENTO — PROCESSOS POR MÊS/ANO
B28: Mês/Ano | C28: Jan | D28: Fev | E28: Mar | F28: Abr | G28: Mai | H28: Jun | I28: Jul | J28: Ago | K28: Set | L28: Out | M28: Nov | N28: Dez | O28: Total Ano
B29: 2022 | C29: =COUNTIFS('BASE DE DADOS'!$E$4:$E$3000,">="&DATE($B29,MONTH(1&C$28),1),'BASE DE DADOS'!$E$4:$E$3000,"<="&EOMONTH(DATE($B29,MONTH(1&C$28),1),0)) | D29: =COUNTIFS('BASE DE DADOS'!$E$4:$E$3000,">="&DATE($B29,MONTH(1&D$28),1),'BASE DE DADOS'!$E$4:$E$3000,"<="&EOMONTH(DATE($B29,MONTH(1&D$28),1),0)) | E29: =COUNTIFS('BASE DE DADOS'!$E$4:$E$3000,">="&DATE($B29,MONTH(1&E$28),1),'BASE DE DADOS'!$E$4:$E$3000,"<="&EOMONTH(DATE($B29,MONTH(1&E$28),1),0)) | F29: =COUNTIFS('BASE DE DADOS'!$E$4:$E$3000,">="&DATE($B29,MONTH(1&F$28),1),'BASE DE DADOS'!$E$4:$E$3000,"<="&EOMONTH(DATE($B29,MONTH(1&F$28),1),0)) | G29: =COUNTIFS('BASE DE DADOS'!$E$4:$E$3000,">="&DATE($B29,MONTH(1&G$28),1),'BASE DE DADOS'!$E$4:$E$3000,"<="&EOMONTH(DATE($B29,MONTH(1&G$28),1),0)) | H29: =COUNTIFS('BASE DE DADOS'!$E$4:$E$3000,">="&DATE($B29,MONTH(1&H$28),1),'BASE DE DADOS'!$E$4:$E$3000,"<="&EOMONTH(DATE($B29,MONTH(1&H$28),1),0)) | I29: =COUNTIFS('BASE DE DADOS'!$E$4:$E$3000,">="&DATE($B29,MONTH(1&I$28),1),'BASE DE DADOS'!$E$4:$E$3000,"<="&EOMONTH(DATE($B29,MONTH(1&I$28),1),0)) | J29: =COUNTIFS('BASE DE DADOS'!$E$4:$E$3000,">="&DATE($B29,MONTH(1&J$28),1),'BASE DE DADOS'!$E$4:$E$3000,"<="&EOMONTH(DATE($B29,MONTH(1&J$28),1),0)) | ... N29: =COUNTIFS('BASE DE DADOS'!$E$4:$E$3000,">="&DATE($B29,MONTH(1&N$28),1),'BASE DE DADOS'!$E$4:$E$3000,"<="&EOMONTH(DATE($B29,MONTH(1&N$28),1),0)) | O29: =SUM(C29:N29)
B30: 2023 | C30: =COUNTIFS('BASE DE DADOS'!$E$4:$E$3000,">="&DATE($B30,MONTH(1&C$28),1),'BASE DE DADOS'!$E$4:$E$3000,"<="&EOMONTH(DATE($B30,MONTH(1&C$28),1),0)) | D30: =COUNTIFS('BASE DE DADOS'!$E$4:$E$3000,">="&DATE($B30,MONTH(1&D$28),1),'BASE DE DADOS'!$E$4:$E$3000,"<="&EOMONTH(DATE($B30,MONTH(1&D$28),1),0)) | E30: =COUNTIFS('BASE DE DADOS'!$E$4:$E$3000,">="&DATE($B30,MONTH(1&E$28),1),'BASE DE DADOS'!$E$4:$E$3000,"<="&EOMONTH(DATE($B30,MONTH(1&E$28),1),0)) | F30: =COUNTIFS('BASE DE DADOS'!$E$4:$E$3000,">="&DATE($B30,MONTH(1&F$28),1),'BASE DE DADOS'!$E$4:$E$3000,"<="&EOMONTH(DATE($B30,MONTH(1&F$28),1),0)) | G30: =COUNTIFS('BASE DE DADOS'!$E$4:$E$3000,">="&DATE($B30,MONTH(1&G$28),1),'BASE DE DADOS'!$E$4:$E$3000,"<="&EOMONTH(DATE($B30,MONTH(1&G$28),1),0)) | H30: =COUNTIFS('BASE DE DADOS'!$E$4:$E$3000,">="&DATE($B30,MONTH(1&H$28),1),'BASE DE DADOS'!$E$4:$E$3000,"<="&EOMONTH(DATE($B30,MONTH(1&H$28),1),0)) | I30: =COUNTIFS('BASE DE DADOS'!$E$4:$E$3000,">="&DATE($B30,MONTH(1&I$28),1),'BASE DE DADOS'!$E$4:$E$3000,"<="&EOMONTH(DATE($B30,MONTH(1&I$28),1),0)) | J30: =COUNTIFS('BASE DE DADOS'!$E$4:$E$3000,">="&DATE($B30,MONTH(1&J$28),1),'BASE DE DADOS'!$E$4:$E$3000,"<="&EOMONTH(DATE($B30,MONTH(1&J$28),1),0)) | ... N30: =COUNTIFS('BASE DE DADOS'!$E$4:$E$3000,">="&DATE($B30,MONTH(1&N$28),1),'BASE DE DADOS'!$E$4:$E$3000,"<="&EOMONTH(DATE($B30,MONTH(1&N$28),1),0)) | O30: =SUM(C30:N30)
B31: 2024 | C31: =COUNTIFS('BASE DE DADOS'!$E$4:$E$3000,">="&DATE($B31,MONTH(1&C$28),1),'BASE DE DADOS'!$E$4:$E$3000,"<="&EOMONTH(DATE($B31,MONTH(1&C$28),1),0)) | D31: =COUNTIFS('BASE DE DADOS'!$E$4:$E$3000,">="&DATE($B31,MONTH(1&D$28),1),'BASE DE DADOS'!$E$4:$E$3000,"<="&EOMONTH(DATE($B31,MONTH(1&D$28),1),0)) | E31: =COUNTIFS('BASE DE DADOS'!$E$4:$E$3000,">="&DATE($B31,MONTH(1&E$28),1),'BASE DE DADOS'!$E$4:$E$3000,"<="&EOMONTH(DATE($B31,MONTH(1&E$28),1),0)) | F31: =COUNTIFS('BASE DE DADOS'!$E$4:$E$3000,">="&DATE($B31,MONTH(1&F$28),1),'BASE DE DADOS'!$E$4:$E$3000,"<="&EOMONTH(DATE($B31,MONTH(1&F$28),1),0)) | G31: =COUNTIFS('BASE DE DADOS'!$E$4:$E$3000,">="&DATE($B31,MONTH(1&G$28),1),'BASE DE DADOS'!$E$4:$E$3000,"<="&EOMONTH(DATE($B31,MONTH(1&G$28),1),0)) | H31: =COUNTIFS('BASE DE DADOS'!$E$4:$E$3000,">="&DATE($B31,MONTH(1&H$28),1),'BASE DE DADOS'!$E$4:$E$3000,"<="&EOMONTH(DATE($B31,MONTH(1&H$28),1),0)) | I31: =COUNTIFS('BASE DE DADOS'!$E$4:$E$3000,">="&DATE($B31,MONTH(1&I$28),1),'BASE DE DADOS'!$E$4:$E$3000,"<="&EOMONTH(DATE($B31,MONTH(1&I$28),1),0)) | J31: =COUNTIFS('BASE DE DADOS'!$E$4:$E$3000,">="&DATE($B31,MONTH(1&J$28),1),'BASE DE DADOS'!$E$4:$E$3000,"<="&EOMONTH(DATE($B31,MONTH(1&J$28),1),0)) | ... N31: =COUNTIFS('BASE DE DADOS'!$E$4:$E$3000,">="&DATE($B31,MONTH(1&N$28),1),'BASE DE DADOS'!$E$4:$E$3000,"<="&EOMONTH(DATE($B31,MONTH(1&N$28),1),0)) | O31: =SUM(C31:N31)
B32: 2025 | C32: =COUNTIFS('BASE DE DADOS'!$E$4:$E$3000,">="&DATE($B32,MONTH(1&C$28),1),'BASE DE DADOS'!$E$4:$E$3000,"<="&EOMONTH(DATE($B32,MONTH(1&C$28),1),0)) | D32: =COUNTIFS('BASE DE DADOS'!$E$4:$E$3000,">="&DATE($B32,MONTH(1&D$28),1),'BASE DE DADOS'!$E$4:$E$3000,"<="&EOMONTH(DATE($B32,MONTH(1&D$28),1),0)) | E32: =COUNTIFS('BASE DE DADOS'!$E$4:$E$3000,">="&DATE($B32,MONTH(1&E$28),1),'BASE DE DADOS'!$E$4:$E$3000,"<="&EOMONTH(DATE($B32,MONTH(1&E$28),1),0)) | F32: =COUNTIFS('BASE DE DADOS'!$E$4:$E$3000,">="&DATE($B32,MONTH(1&F$28),1),'BASE DE DADOS'!$E$4:$E$3000,"<="&EOMONTH(DATE($B32,MONTH(1&F$28),1),0)) | G32: =COUNTIFS('BASE DE DADOS'!$E$4:$E$3000,">="&DATE($B32,MONTH(1&G$28),1),'BASE DE DADOS'!$E$4:$E$3000,"<="&EOMONTH(DATE($B32,MONTH(1&G$28),1),0)) | H32: =COUNTIFS('BASE DE DADOS'!$E$4:$E$3000,">="&DATE($B32,MONTH(1&H$28),1),'BASE DE DADOS'!$E$4:$E$3000,"<="&EOMONTH(DATE($B32,MONTH(1&H$28),1),0)) | I32: =COUNTIFS('BASE DE DADOS'!$E$4:$E$3000,">="&DATE($B32,MONTH(1&I$28),1),'BASE DE DADOS'!$E$4:$E$3000,"<="&EOMONTH(DATE($B32,MONTH(1&I$28),1),0)) | J32: =COUNTIFS('BASE DE DADOS'!$E$4:$E$3000,">="&DATE($B32,MONTH(1&J$28),1),'BASE DE DADOS'!$E$4:$E$3000,"<="&EOMONTH(DATE($B32,MONTH(1&J$28),1),0)) | ... N32: =COUNTIFS('BASE DE DADOS'!$E$4:$E$3000,">="&DATE($B32,MONTH(1&N$28),1),'BASE DE DADOS'!$E$4:$E$3000,"<="&EOMONTH(DATE($B32,MONTH(1&N$28),1),0)) | O32: =SUM(C32:N32)
B33: 2026 | C33: =COUNTIFS('BASE DE DADOS'!$E$4:$E$3000,">="&DATE($B33,MONTH(1&C$28),1),'BASE DE DADOS'!$E$4:$E$3000,"<="&EOMONTH(DATE($B33,MONTH(1&C$28),1),0)) | D33: =COUNTIFS('BASE DE DADOS'!$E$4:$E$3000,">="&DATE($B33,MONTH(1&D$28),1),'BASE DE DADOS'!$E$4:$E$3000,"<="&EOMONTH(DATE($B33,MONTH(1&D$28),1),0)) | E33: =COUNTIFS('BASE DE DADOS'!$E$4:$E$3000,">="&DATE($B33,MONTH(1&E$28),1),'BASE DE DADOS'!$E$4:$E$3000,"<="&EOMONTH(DATE($B33,MONTH(1&E$28),1),0)) | F33: =COUNTIFS('BASE DE DADOS'!$E$4:$E$3000,">="&DATE($B33,MONTH(1&F$28),1),'BASE DE DADOS'!$E$4:$E$3000,"<="&EOMONTH(DATE($B33,MONTH(1&F$28),1),0)) | G33: =COUNTIFS('BASE DE DADOS'!$E$4:$E$3000,">="&DATE($B33,MONTH(1&G$28),1),'BASE DE DADOS'!$E$4:$E$3000,"<="&EOMONTH(DATE($B33,MONTH(1&G$28),1),0)) | H33: =COUNTIFS('BASE DE DADOS'!$E$4:$E$3000,">="&DATE($B33,MONTH(1&H$28),1),'BASE DE DADOS'!$E$4:$E$3000,"<="&EOMONTH(DATE($B33,MONTH(1&H$28),1),0)) | I33: =COUNTIFS('BASE DE DADOS'!$E$4:$E$3000,">="&DATE($B33,MONTH(1&I$28),1),'BASE DE DADOS'!$E$4:$E$3000,"<="&EOMONTH(DATE($B33,MONTH(1&I$28),1),0)) | J33: =COUNTIFS('BASE DE DADOS'!$E$4:$E$3000,">="&DATE($B33,MONTH(1&J$28),1),'BASE DE DADOS'!$E$4:$E$3000,"<="&EOMONTH(DATE($B33,MONTH(1&J$28),1),0)) | ... N33: =COUNTIFS('BASE DE DADOS'!$E$4:$E$3000,">="&DATE($B33,MONTH(1&N$28),1),'BASE DE DADOS'!$E$4:$E$3000,"<="&EOMONTH(DATE($B33,MONTH(1&N$28),1),0)) | O33: =SUM(C33:N33)
B34: TOTAL | C34: =SUM(C29:C33) | D34: =SUM(D29:D33) | E34: =SUM(E29:E33) | F34: =SUM(F29:F33) | G34: =SUM(G29:G33) | H34: =SUM(H29:H33) | I34: =SUM(I29:I33) | J34: =SUM(J29:J33) | ... N34: =SUM(N29:N33)
B63: K Controllers | kcontrollers.com.br | Controladoria Jurídica na prática.

Sheet PRODUTIVIDADE E PRAZOS
A1: PRODUTIVIDADE E GESTÃO DE PRAZOS
A2: Produtividade com dados de 01.01.2026 a 28.02.2026
A3: Atualização automática a partir da BASE DE DADOS | Não edite esta aba
B5: PAINEL GERAL DE PRAZOS
B6: Indicador | C6: Qtd. | D6: % do Total
B7: Total de Prazos Cadastrados | C7: =COUNTA('BASE DE DADOS'!$M$4:$M$3000) | D7: =IF(C7=0,"-","100%")
B8: ✔ Prazos Cumpridos | C8: =COUNTIF('BASE DE DADOS'!$M$4:$M$3000,"Cumprido") | D8: =IF(C7=0,"-",TEXT(C8/C7,"0.0%"))
B9: ⏳ Prazos Pendentes | C9: =COUNTIF('BASE DE DADOS'!$M$4:$M$3000,"Pendente") | D9: =IF(C7=0,"-",TEXT(C9/C7,"0.0%"))
B10: ✘ Prazos Não Cumpridos | C10: =COUNTIF('BASE DE DADOS'!$M$4:$M$3000,"Não cumprido") | D10: =IF(C7=0,"-",TEXT(C10/C7,"0.0%"))
B11: TAXA DE CUMPRIMENTO DE PRAZOS | D11: =IF(C7=0,"-",TEXT(C8/(C8+C10),"0.0%")) | E11: ← Cumpridos ÷ (Cumpridos + Não cumpridos)
B13: PRAZOS POR TIPO
B14: Tipo de Prazo | C14: Total | D14: Cumpridos | E14: Não Cumpridos | F14: Taxa (%)
B15: Contestação | C15: =COUNTIF('BASE DE DADOS'!$J$4:$J$3000,B15) | D15: {=SUMPRODUCT(('BASE DE DADOS'!$J$4:$J$3000=B15)*('BASE DE DADOS'!$M$4:$M$3000="Cumprido"))} | E15: {=SUMPRODUCT(('BASE DE DADOS'!$J$4:$J$3000=B15)*('BASE DE DADOS'!$M$4:$M$3000="Não cumprido"))} | F15: =IF(C15=0,"-",TEXT(D15/C15,"0.0%"))
B16: Recurso de Apelação | C16: =COUNTIF('BASE DE DADOS'!$J$4:$J$3000,B16) | D16: {=SUMPRODUCT(('BASE DE DADOS'!$J$4:$J$3000=B16)*('BASE DE DADOS'!$M$4:$M$3000="Cumprido"))} | E16: {=SUMPRODUCT(('BASE DE DADOS'!$J$4:$J$3000=B16)*('BASE DE DADOS'!$M$4:$M$3000="Não cumprido"))} | F16: =IF(C16=0,"-",TEXT(D16/C16,"0.0%"))
B17: Agravo | C17: =COUNTIF('BASE DE DADOS'!$J$4:$J$3000,B17) | D17: {=SUMPRODUCT(('BASE DE DADOS'!$J$4:$J$3000=B17)*('BASE DE DADOS'!$M$4:$M$3000="Cumprido"))} | E17: {=SUMPRODUCT(('BASE DE DADOS'!$J$4:$J$3000=B17)*('BASE DE DADOS'!$M$4:$M$3000="Não cumprido"))} | F17: =IF(C17=0,"-",TEXT(D17/C17,"0.0%"))
B18: Manifestação | C18: =COUNTIF('BASE DE DADOS'!$J$4:$J$3000,B18) | D18: {=SUMPRODUCT(('BASE DE DADOS'!$J$4:$J$3000=B18)*('BASE DE DADOS'!$M$4:$M$3000="Cumprido"))} | E18: {=SUMPRODUCT(('BASE DE DADOS'!$J$4:$J$3000=B18)*('BASE DE DADOS'!$M$4:$M$3000="Não cumprido"))} | F18: =IF(C18=0,"-",TEXT(D18/C18,"0.0%"))
B19: Contrarrazões | C19: =COUNTIF('BASE DE DADOS'!$J$4:$J$3000,B19) | D19: {=SUMPRODUCT(('BASE DE DADOS'!$J$4:$J$3000=B19)*('BASE DE DADOS'!$M$4:$M$3000="Cumprido"))} | E19: {=SUMPRODUCT(('BASE DE DADOS'!$J$4:$J$3000=B19)*('BASE DE DADOS'!$M$4:$M$3000="Não cumprido"))} | F19: =IF(C19=0,"-",TEXT(D19/C19,"0.0%"))
B20: Audiência | C20: =COUNTIF('BASE DE DADOS'!$J$4:$J$3000,B20) | D20: {=SUMPRODUCT(('BASE DE DADOS'!$J$4:$J$3000=B20)*('BASE DE DADOS'!$M$4:$M$3000="Cumprido"))} | E20: {=SUMPRODUCT(('BASE DE DADOS'!$J$4:$J$3000=B20)*('BASE DE DADOS'!$M$4:$M$3000="Não cumprido"))} | F20: =IF(C20=0,"-",TEXT(D20/C20,"0.0%"))
B21: Embargos | C21: =COUNTIF('BASE DE DADOS'!$J$4:$J$3000,B21) | D21: {=SUMPRODUCT(('BASE DE DADOS'!$J$4:$J$3000=B21)*('BASE DE DADOS'!$M$4:$M$3000="Cumprido"))} | E21: {=SUMPRODUCT(('BASE DE DADOS'!$J$4:$J$3000=B21)*('BASE DE DADOS'!$M$4:$M$3000="Não cumprido"))} | F21: =IF(C21=0,"-",TEXT(D21/C21,"0.0%"))
B22: Evento | C22: =COUNTIF('BASE DE DADOS'!$J$4:$J$3000,B22) | D22: {=SUMPRODUCT(('BASE DE DADOS'!$J$4:$J$3000=B22)*('BASE DE DADOS'!$M$4:$M$3000="Cumprido"))} | E22: {=SUMPRODUCT(('BASE DE DADOS'!$J$4:$J$3000=B22)*('BASE DE DADOS'!$M$4:$M$3000="Não cumprido"))}
B23: Prazo | C23: =COUNTIF('BASE DE DADOS'!$J$4:$J$3000,B23) | D23: {=SUMPRODUCT(('BASE DE DADOS'!$J$4:$J$3000=B23)*('BASE DE DADOS'!$M$4:$M$3000="Cumprido"))} | E23: {=SUMPRODUCT(('BASE DE DADOS'!$J$4:$J$3000=B23)*('BASE DE DADOS'!$M$4:$M$3000="Não cumprido"))}
B24: Tarefa | C24: =COUNTIF('BASE DE DADOS'!$J$4:$J$3000,B24) | D24: {=SUMPRODUCT(('BASE DE DADOS'!$J$4:$J$3000=B24)*('BASE DE DADOS'!$M$4:$M$3000="Cumprido"))} | E24: {=SUMPRODUCT(('BASE DE DADOS'!$J$4:$J$3000=B24)*('BASE DE DADOS'!$M$4:$M$3000="Não cumprido"))}
B25: Outros | C25: =COUNTIF('BASE DE DADOS'!$J$4:$J$3000,B25) | D25: {=SUMPRODUCT(('BASE DE DADOS'!$J$4:$J$3000=B25)*('BASE DE DADOS'!$M$4:$M$3000="Cumprido"))} | E25: {=SUMPRODUCT(('BASE DE DADOS'!$J$4:$J$3000=B25)*('BASE DE DADOS'!$M$4:$M$3000="Não cumprido"))} | F25: =IF(C25=0,"-",TEXT(D25/C25,"0.0%"))
B27: PERFORMANCE POR ADVOGADO - PRAZOS
B28: Responsável | C28: Total Prazos | D28: Cumpridos | E28: Não Cumpridos | F28: Taxa (%)
B29: Ronaldo Koyama | C29: =IF(B29="","",COUNTIF('BASE DE DADOS'!$L$4:$L$3000,B29)) | D29: {=IF(B29="","",SUMPRODUCT(('BASE DE DADOS'!$L$4:$L$3000=B29)*('BASE DE DADOS'!$M$4:$M$3000="Cumprido")))} | E29: {=IF(B29="","",SUMPRODUCT(('BASE DE DADOS'!$L$4:$L$3000=B29)*('BASE DE DADOS'!$M$4:$M$3000="Não cumprido")))} | F29: =IF(OR(B29="",C29=0),"-",TEXT(D29/C29,"0.0%"))
B30: Lucas | C30: =IF(B30="","",COUNTIF('BASE DE DADOS'!$L$4:$L$3000,B30)) | D30: {=IF(B30="","",SUMPRODUCT(('BASE DE DADOS'!$L$4:$L$3000=B30)*('BASE DE DADOS'!$M$4:$M$3000="Cumprido")))} | E30: {=IF(B30="","",SUMPRODUCT(('BASE DE DADOS'!$L$4:$L$3000=B30)*('BASE DE DADOS'!$M$4:$M$3000="Não cumprido")))} | F30: =IF(OR(B30="",C30=0),"-",TEXT(D30/C30,"0.0%"))
B31: Luci | C31: =IF(B31="","",COUNTIF('BASE DE DADOS'!$L$4:$L$3000,B31)) | D31: {=IF(B31="","",SUMPRODUCT(('BASE DE DADOS'!$L$4:$L$3000=B31)*('BASE DE DADOS'!$M$4:$M$3000="Cumprido")))} | E31: {=IF(B31="","",SUMPRODUCT(('BASE DE DADOS'!$L$4:$L$3000=B31)*('BASE DE DADOS'!$M$4:$M$3000="Não cumprido")))} | F31: =IF(OR(B31="",C31=0),"-",TEXT(D31/C31,"0.0%"))
B32: Julia | C32: =IF(B32="","",COUNTIF('BASE DE DADOS'!$L$4:$L$3000,B32)) | D32: {=IF(B32="","",SUMPRODUCT(('BASE DE DADOS'!$L$4:$L$3000=B32)*('BASE DE DADOS'!$M$4:$M$3000="Cumprido")))} | E32: {=IF(B32="","",SUMPRODUCT(('BASE DE DADOS'!$L$4:$L$3000=B32)*('BASE DE DADOS'!$M$4:$M$3000="Não cumprido")))} | F32: =IF(OR(B32="",C32=0),"-",TEXT(D32/C32,"0.0%"))
B33: Pedro Victor | C33: =IF(B33="","",COUNTIF('BASE DE DADOS'!$L$4:$L$3000,B33)) | D33: {=IF(B33="","",SUMPRODUCT(('BASE DE DADOS'!$L$4:$L$3000=B33)*('BASE DE DADOS'!$M$4:$M$3000="Cumprido")))} | E33: {=IF(B33="","",SUMPRODUCT(('BASE DE DADOS'!$L$4:$L$3000=B33)*('BASE DE DADOS'!$M$4:$M$3000="Não cumprido")))} | F33: =IF(OR(B33="",C33=0),"-",TEXT(D33/C33,"0.0%"))
B34: Alexia | C34: =IF(B34="","",COUNTIF('BASE DE DADOS'!$L$4:$L$3000,B34)) | D34: {=IF(B34="","",SUMPRODUCT(('BASE DE DADOS'!$L$4:$L$3000=B34)*('BASE DE DADOS'!$M$4:$M$3000="Cumprido")))} | E34: {=IF(B34="","",SUMPRODUCT(('BASE DE DADOS'!$L$4:$L$3000=B34)*('BASE DE DADOS'!$M$4:$M$3000="Não cumprido")))} | F34: =IF(OR(B34="",C34=0),"-",TEXT(D34/C34,"0.0%"))
B35: Jessica | C35: =IF(B35="","",COUNTIF('BASE DE DADOS'!$L$4:$L$3000,B35)) | D35: {=IF(B35="","",SUMPRODUCT(('BASE DE DADOS'!$L$4:$L$3000=B35)*('BASE DE DADOS'!$M$4:$M$3000="Cumprido")))} | E35: {=IF(B35="","",SUMPRODUCT(('BASE DE DADOS'!$L$4:$L$3000=B35)*('BASE DE DADOS'!$M$4:$M$3000="Não cumprido")))} | F35: =IF(OR(B35="",C35=0),"-",TEXT(D35/C35,"0.0%"))
B36: Marelize Controladoria | C36: =IF(B36="","",COUNTIF('BASE DE DADOS'!$L$4:$L$3000,B36)) | D36: {=IF(B36="","",SUMPRODUCT(('BASE DE DADOS'!$L$4:$L$3000=B36)*('BASE DE DADOS'!$M$4:$M$3000="Cumprido")))} | E36: {=IF(B36="","",SUMPRODUCT(('BASE DE DADOS'!$L$4:$L$3000=B36)*('BASE DE DADOS'!$M$4:$M$3000="Não cumprido")))} | F36: =IF(OR(B36="",C36=0),"-",TEXT(D36/C36,"0.0%"))
B37: Renata Francisco Becker | C37: =IF(B37="","",COUNTIF('BASE DE DADOS'!$L$4:$L$3000,B37)) | D37: {=IF(B37="","",SUMPRODUCT(('BASE DE DADOS'!$L$4:$L$3000=B37)*('BASE DE DADOS'!$M$4:$M$3000="Cumprido")))} | E37: {=IF(B37="","",SUMPRODUCT(('BASE DE DADOS'!$L$4:$L$3000=B37)*('BASE DE DADOS'!$M$4:$M$3000="Não cumprido")))} | F37: =IF(OR(B37="",C37=0),"-",TEXT(D37/C37,"0.0%"))
A42: K Controllers | kcontrollers.com.br | Controladoria Jurídica na prática.
